{
  "generated_at": "2026-05-22T22:00:11.833134",
  "article_count": 5,
  "articles": [
    {
      "title": "Global Perspective on Flask Quality Standards Lfgb Fda from Chinese Manufacturers",
      "slug": "global-perspective-on-flask-quality-standards-lfgb-fda-from-",
      "date": "May 22, 2026",
      "category": "Industry"
    },
    {
      "title": "The Science Behind Flask Cleaning And Maintenance: Technical Deep Dive",
      "slug": "the-science-behind-flask-cleaning-and-maintenance-technical-",
      "date": "May 22, 2026",
      "category": "Technology"
    },
    {
      "title": "Maximizing Performance: Coffee Pot Retention Technology Recommendations",
      "slug": "maximizing-performance-coffee-pot-retention-technology-recom",
      "date": "May 22, 2026",
      "category": "Usage"
    },
    {
      "title": "From Raw Material to Drinkware Industry: Our Production Journey",
      "slug": "from-raw-material-to-drinkware-industry-our-production-journ",
      "date": "May 22, 2026",
      "category": "Factory"
    },
    {
      "title": "Market Trends: How Food Grade Flask Safety is Shaping the Industry",
      "slug": "market-trends-how-food-grade-flask-safety-is-shaping-the-ind",
      "date": "May 22, 2026",
      "category": "Industry"
    }
  ]
}